{
  "_TITLE": "THIS FILE IS AUTOGENERATED -- DO NOT MAKE CHANGES!",
  "_INFO": "Created using ./scripts/bin/compile-scss-variables.sh from ./docs/_data/variables.json",
  "headerLogo": "hv-hl",
  "products": "hv-p",
  "provider": "hv-pp",
  "name": "hv-pn",
  "disk": "hv-pi",
  "price": "hv-pr",
  "textHeightImage": "hv-thi",
  "verticalNav": "hv-nv",
  "navItem": "hv-ni",
  "selectedNavItem": "hv-sni",
  "navContent": "hv-nc",
  "primaryContent": "hv-pc",
  "secondaryContent": "hv-sc",
  "mascot": "hv-m",
  "pageDate": "hv-pd"
}
